Metadata-Version: 2.1
Name: odoo-addon-stay
Version: 16.0.1.2.0.18
Summary: Simple management of stays and meals
Home-page: https://github.com/OCA/vertical-abbey
Author: Barroux Abbey, Akretion, Odoo Community Association (OCA)
Author-email: support@odoo-community.org
License: AGPL-3
Classifier: Programming Language :: Python
Classifier: Framework :: Odoo
Classifier: Framework :: Odoo :: 16.0
Classifier: License :: OSI Approved :: GNU Affero General Public License v3
Requires-Python: >=3.10
Requires-Dist: odoo-addon-web-timeline<16.1dev,>=16.0dev
Requires-Dist: odoo<16.1dev,>=16.0a
Requires-Dist: xlsxwriter
